README.md
setup.py
alephvault/http_storage/generators/__init__.py
alephvault/http_storage/generators/project.py
alephvault/http_storage/generators/templates/multichar-application-template.py
alephvault/http_storage/generators/templates/simple-application-template.py
alephvault_windrose_http_mongodb_storage_generator.egg-info/PKG-INFO
alephvault_windrose_http_mongodb_storage_generator.egg-info/SOURCES.txt
alephvault_windrose_http_mongodb_storage_generator.egg-info/dependency_links.txt
alephvault_windrose_http_mongodb_storage_generator.egg-info/requires.txt
alephvault_windrose_http_mongodb_storage_generator.egg-info/top_level.txt