Metadata-Version: 2.1
Name: alephvault-windrose-http-mongodb-storage-generator
Version: 0.0.8
Summary: A generator of production-ready HTTP storage stacks for WindRose/NetRose games
Home-page: https://github.com/AlephVault/python-windrose-http-storage-generator
Author: luismasuelli
Author-email: luismasuelli@hotmail.com
License: MIT
